{"dependencies":[{"name":"../vendor/glamor/hash","loc":{"line":5,"column":20}},{"name":"../models/StyleSheet","loc":{"line":9,"column":26}},{"name":"../types","loc":{"line":19,"column":67}},{"name":"prop-types","loc":{"line":19,"column":143}}],"generated":{"js":"'use strict';\n\nexports.__esModule = true;\n\nvar _hash = require('../vendor/glamor/hash');\n\nvar _hash2 = _interopRequireDefault(_hash);\n\nvar _StyleSheet = require('../models/StyleSheet');\n\nvar _StyleSheet2 = _interopRequireDefault(_StyleSheet);\n\nfunction _interopRequireDefault(obj) { return obj && obj.__esModule ? obj : { default: obj }; }\n\nvar babelPluginFlowReactPropTypes_proptype_Stringifier = require('../types').babelPluginFlowReactPropTypes_proptype_Stringifier || require('prop-types').any;\n\nvar babelPluginFlowReactPropTypes_proptype_NameGenerator = require('../types').babelPluginFlowReactPropTypes_proptype_NameGenerator || require('prop-types').any;\n\nvar babelPluginFlowReactPropTypes_proptype_Interpolation = require('../types').babelPluginFlowReactPropTypes_proptype_Interpolation || require('prop-types').any;\n\nvar replaceWhitespace = function replaceWhitespace(str) {\n  return str.replace(/\\s|\\\\n/g, '');\n};\n\nexports.default = function (nameGenerator, stringifyRules, css) {\n  return function (strings) {\n    for (var _len = arguments.length, interpolations = Array(_len > 1 ? _len - 1 : 0), _key = 1; _key < _len; _key++) {\n      interpolations[_key - 1] = arguments[_key];\n    }\n\n    var rules = css.apply(undefined, [strings].concat(interpolations));\n    var hash = (0, _hash2.default)(replaceWhitespace(JSON.stringify(rules)));\n\n    var existingName = _StyleSheet2.default.instance.getName(hash);\n    if (existingName) return existingName;\n\n    var name = nameGenerator(hash);\n    if (_StyleSheet2.default.instance.alreadyInjected(hash, name)) return name;\n\n    var generatedCSS = stringifyRules(rules, name, '@keyframes');\n    _StyleSheet2.default.instance.inject('sc-keyframes-' + name, true, generatedCSS, hash, name);\n    return name;\n  };\n};\n\nmodule.exports = exports['default'];"},"hash":"8e2a78f4d58a930e8bcd508e3d074997"}