{"dependencies":[{"name":"fbjs/lib/hyphenateStyleName","loc":{"line":6,"column":34}},{"name":"is-plain-object","loc":{"line":10,"column":29}},{"name":"../types","loc":{"line":16,"column":67}},{"name":"prop-types","loc":{"line":16,"column":143}}],"generated":{"js":"'use strict';\n\nexports.__esModule = true;\nexports.objToCss = undefined;\n\nvar _hyphenateStyleName = require('fbjs/lib/hyphenateStyleName');\n\nvar _hyphenateStyleName2 = _interopRequireDefault(_hyphenateStyleName);\n\nvar _isPlainObject = require('is-plain-object');\n\nvar _isPlainObject2 = _interopRequireDefault(_isPlainObject);\n\nfunction _interopRequireDefault(obj) { return obj && obj.__esModule ? obj : { default: obj }; }\n\nvar babelPluginFlowReactPropTypes_proptype_Interpolation = require('../types').babelPluginFlowReactPropTypes_proptype_Interpolation || require('prop-types').any;\n\nvar objToCss = exports.objToCss = function objToCss(obj, prevKey) {\n  var css = Object.keys(obj).filter(function (key) {\n    var chunk = obj[key];\n    return chunk !== undefined && chunk !== null && chunk !== false && chunk !== '';\n  }).map(function (key) {\n    if ((0, _isPlainObject2.default)(obj[key])) return objToCss(obj[key], key);\n    return (0, _hyphenateStyleName2.default)(key) + ': ' + obj[key] + ';';\n  }).join(' ');\n  return prevKey ? prevKey + ' {\\n  ' + css + '\\n}' : css;\n};\n\nvar flatten = function flatten(chunks, executionContext) {\n  return chunks.reduce(function (ruleSet, chunk) {\n    /* Remove falsey values */\n    if (chunk === undefined || chunk === null || chunk === false || chunk === '') return ruleSet;\n    /* Flatten ruleSet */\n    if (Array.isArray(chunk)) return [].concat(ruleSet, flatten(chunk, executionContext));\n\n    /* Handle other components */\n    // $FlowFixMe not sure how to make this pass\n    if (chunk.hasOwnProperty('styledComponentId')) return [].concat(ruleSet, ['.' + chunk.styledComponentId]);\n\n    /* Either execute or defer the function */\n    if (typeof chunk === 'function') {\n      return executionContext ? ruleSet.concat.apply(ruleSet, flatten([chunk(executionContext)], executionContext)) : ruleSet.concat(chunk);\n    }\n\n    /* Handle objects */\n    // $FlowFixMe have to add %checks somehow to isPlainObject\n    return ruleSet.concat((0, _isPlainObject2.default)(chunk) ? objToCss(chunk) : chunk.toString());\n  }, []);\n};\n\nexports.default = flatten;"},"hash":"d5bd41e1026af3829404e862466b4165"}